[
    {
        "image1" : "https://a0.muscache.com/im/pictures/7a0735b6-b341-4d2c-a0ab-8fa01d1373fb.jpg?im_q=medq&im_w=240",
        "image2" : "https://a0.muscache.com/im/pictures/a0eb36e7-b468-4c5e-93b2-819e793563b2.jpg?im_q=medq&im_w=240",
        "heading1" : "Murree",
        "heading2" : "Peshawar",
        "text1" : "1 hour drive",
        "text2" : "2.5 hour drive"
    },
    {
        "image1" : "https://a0.muscache.com/im/pictures/926d56aa-8b36-4138-8eae-ad991868b858.jpg?im_q=medq&im_w=240",
        "image2" : "https://a0.muscache.com/im/pictures/85bd76fe-3c73-4e79-b581-36b9676892f7.jpg?im_q=medq&im_w=240",
        "heading1" : "Lahore",
        "heading2" : "Faisalabad",
        "text1" : "4.5 hour drive",
        "text2" : "4 hour drive"
    },
    {
        "image1" : "https://a0.muscache.com/im/pictures/087a8dff-a609-4084-86db-f45051c6f23a.jpg?im_q=medq&im_w=240",
        "image2" : "https://a0.muscache.com/im/pictures/f98fbb2e-9e10-4514-b4a7-02c467e1da03.jpg?im_q=medq&im_w=240",
        "heading1" : "Rawalpindi Cantt",
        "heading2" : "Multan",
        "text1" : "30 minute drive",
        "text2" : "6 hour drive"
    },
    {
        "image1" : "https://a0.muscache.com/im/pictures/558a403a-aeed-4829-83a6-c9b0ccf21866.jpg?im_q=medq&im_w=240",
        "image2" : "https://a0.muscache.com/im/pictures/ac2086c9-df0d-4085-94c0-94fe3fb94862.jpg?im_q=medq&im_w=240",
        "heading1" : "Abbottabad",
        "heading2" : "2 hour drive",
        "text1" : "Gujranwala",
        "text2" : "3.5 hour drive"
    }
]